vz_recommender/__init__.py
vz_recommender/models/__init__.py
vz_recommender/models/ae.py
vz_recommender/models/attention.py
vz_recommender/models/bst.py
vz_recommender/models/callbacks.py
vz_recommender/models/context.py
vz_recommender/models/encoders.py
vz_recommender/models/grec.py
vz_recommender/models/infinite_attention.py
vz_recommender/models/linear_attention.py
vz_recommender/models/mmoe.py
vz_recommender/models/moe.py
vz_recommender/models/multitask.py
vz_recommender/models/nlp.py
vz_recommender/models/transformer.py
vz_recommender/models/txt.py
vz_recommender/models/utils.py
vz_recommender/utils/__init__.py
vz_recommender/utils/callbacks_base.py
vz_recommender/utils/loggers_base.py
vz_recommender/utils/utils.py
vz_recommender-0.5.4.dist-info/LICENSE
vz_recommender-0.5.4.dist-info/METADATA
vz_recommender-0.5.4.dist-info/WHEEL
vz_recommender-0.5.4.dist-info/top_level.txt
vz_recommender-0.5.4.dist-info/RECORD
