Metadata-Version: 2.1
Name: vz-recommender
Version: 0.5.4
Summary: vz recommender package
Author: lu
Author-email: luyang.wang@verizon.com
Classifier: Programming Language :: Python :: 3
Classifier: License :: OSI Approved :: Apache Software License
Classifier: Operating System :: OS Independent
Requires-Python: >=3.5
License-File: LICENSE
